generate/__init__.py
generate/api/__init__.py
generate/api/generator.py
pytglib/__init__.py
pytglib/client.py
pytglib/functions.py
pytglib/proxy.py
pytglib/tdjson.py
pytglib/utils.py
pytglib/worker.py
pytglib/api/__init__.py
pytglib/api/errors/__init__.py
pytglib/api/errors/error.py
pytglib/api/functions/__init__.py
pytglib/api/functions/accept_call.py
pytglib/api/functions/accept_terms_of_service.py
pytglib/api/functions/add_chat_member.py
pytglib/api/functions/add_chat_members.py
pytglib/api/functions/add_contact.py
pytglib/api/functions/add_custom_server_language_pack.py
pytglib/api/functions/add_favorite_sticker.py
pytglib/api/functions/add_local_message.py
pytglib/api/functions/add_log_message.py
pytglib/api/functions/add_network_statistics.py
pytglib/api/functions/add_proxy.py
pytglib/api/functions/add_recent_sticker.py
pytglib/api/functions/add_recently_found_chat.py
pytglib/api/functions/add_saved_animation.py
pytglib/api/functions/add_sticker_to_set.py
pytglib/api/functions/answer_callback_query.py
pytglib/api/functions/answer_custom_query.py
pytglib/api/functions/answer_inline_query.py
pytglib/api/functions/answer_pre_checkout_query.py
pytglib/api/functions/answer_shipping_query.py
pytglib/api/functions/block_user.py
pytglib/api/functions/can_transfer_ownership.py
pytglib/api/functions/cancel_download_file.py
pytglib/api/functions/cancel_upload_file.py
pytglib/api/functions/change_imported_contacts.py
pytglib/api/functions/change_phone_number.py
pytglib/api/functions/change_sticker_set.py
pytglib/api/functions/check_authentication_bot_token.py
pytglib/api/functions/check_authentication_code.py
pytglib/api/functions/check_authentication_password.py
pytglib/api/functions/check_change_phone_number_code.py
pytglib/api/functions/check_chat_invite_link.py
pytglib/api/functions/check_chat_username.py
pytglib/api/functions/check_created_public_chats_limit.py
pytglib/api/functions/check_database_encryption_key.py
Pytglib-0.4.dist-info/LICENSE
Pytglib-0.4.dist-info/METADATA
Pytglib-0.4.dist-info/WHEEL
Pytglib-0.4.dist-info/top_level.txt
Pytglib-0.4.dist-info/RECORD
