Metadata-Version: 2.1
Name: Pytglib
Version: 0.4
Summary: Python library to help you build your own Telegram clients
Home-page: https://github.com/iTeam-co/python-telegram
Author: iTeam
Author-email: co.amirh@gmail.com
License: UNKNOWN
Platform: UNKNOWN
Classifier: Programming Language :: Python :: 3
Classifier: License :: OSI Approved :: MIT License
Classifier: Operating System :: OS Independent
